<?xml version="1.0" encoding="utf-8"?>
<inapp-products>

    <items>

        <item id="com_topface_topface_buy_coins_8" publish-state="published">
            <summary>
                <summary-base>
                    <title>8 coins</title>

                    <description>Coins - Topface internal currency</description>

                </summary-base>

                <summary-localization locale="ru_RU">
                    <title>8 монет</title>

                    <description>Монеты – внутренняя валюта Topface</description>

                </summary-localization>
            </summary>
            <price autofill="false">
                <price-base>0.10</price-base>


                <price-local country="RU">
                3.00
                </price-local>
                <price-local country="EN">1.00</price-local>
            </price>
        </item>

        <item id="com_topface_topface_buy_coins_22" publish-state="published">
            <summary>
                <summary-base>
                    <title>22 coins</title>

                    <description>Coins - Topface internal currency</description>

                </summary-base>

                <summary-localization locale="ru_RU">
                    <title>22 монеты</title>

                    <description>Монеты – внутренняя валюта Topface</description>

                </summary-localization>
            </summary>
            <price autofill="false">
                <price-base>0.10</price-base>


                <price-local country="RU">
                3.00
                </price-local>
                <price-local country="EN">1.00</price-local>
            </price>
        </item>

        <item id="com_topface_topface_buy_coins_30" publish-state="published">
            <summary>
                <summary-base>
                    <title>30 coins</title>

                    <description>Coins - Topface internal currency</description>

                </summary-base>

                <summary-localization locale="ru_RU">
                    <title>30 монет</title>

                    <description>Монеты – внутренняя валюта Topface</description>

                </summary-localization>
            </summary>
            <price autofill="false">
                <price-base>0.10</price-base>


                <price-local country="RU">
                    3.00
                </price-local>
                <price-local country="EN">1.00</price-local>
            </price>
        </item>

        <item id="com_topface_topface_buy_premium_day_1" publish-state="published">
            <summary>
                <summary-base>
                    <title>VIP-status for 1 day</title>

                    <description>You will always have access to all Topface features</description>

                </summary-base>

                <summary-localization locale="ru_RU">
                    <title>VIP-статус на один день</title>

                    <description>Вы всё время будете иметь доступ ко всем возможностям Topface
                    </description>

                </summary-localization>
            </summary>
            <price autofill="false">
                <price-base>0.10</price-base>


                <price-local country="RU">
                    3.00
                </price-local>
                <price-local country="EN">1.00</price-local>
            </price>
        </item>

        <item id="com_topface_topface_buy_premium_day_6" publish-state="published">
            <summary>
                <summary-base>
                    <title>VIP-status for six days</title>

                    <description>You will always have access to all Topface features</description>

                </summary-base>

                <summary-localization locale="ru_RU">
                    <title>VIP-статус на шесть дней</title>

                    <description>Вы всё время будете иметь доступ ко всем возможностям Topface
                    </description>

                </summary-localization>
            </summary>
            <price autofill="false">
                <price-base>0.10</price-base>


                <price-local country="RU">
                    3.00
                </price-local>
                <price-local country="EN">1.00</price-local>
            </price>
        </item>

        <item id="com_topface_topface_buy_premium_day_10" publish-state="published">
            <summary>
                <summary-base>
                    <title>VIP-status for ten days</title>

                    <description>You will always have access to all Topface features</description>

                </summary-base>

                <summary-localization locale="ru_RU">
                    <title>VIP-статус на десять дней</title>

                    <description>Вы всё время будете иметь доступ ко всем возможностям Topface
                    </description>

                </summary-localization>
            </summary>
            <price autofill="false">
                <price-base>0.10</price-base>


                <price-local country="RU">
                    3.00
                </price-local>
                <price-local country="EN">1.00</price-local>
            </price>
        </item>

        <item id="com_topface_topface_buy_likes_1" publish-state="published">
            <summary>
                <summary-base>
                    <title>Pack of likes</title>

                    <description>The number of likes mentioned in the "Pack" guarantees that this
                        number of people will like you
                    </description>

                </summary-base>

                <summary-localization locale="ru_RU">
                    <title>Пакет симпатий</title>

                    <description>Количество симпатий, указанных в «Пакете», гарантирует, что вы
                        понравитесь этому количеству людей
                    </description>

                </summary-localization>
            </summary>
            <price autofill="false">
                <price-base>0.10</price-base>


                <price-local country="RU">
                3.00
                </price-local>
                <price-local country="EN">1.00</price-local>
            </price>
        </item>
    </items>
</inapp-products>